gittool-0.1.10.dist-info/METADATA
gittool-0.1.10.dist-info/WHEEL
gittool-0.1.10.dist-info/entry_points.txt
gittool/__init__.py
gittool/use.py
gittool-0.1.10.dist-info/RECORD
