Metadata-Version: 2.1
Name: gittool
Version: 0.1.10
Summary: gittool
Author-Email: Jimmy Lin <b00502013@gmail.com>
License: MIT
Requires-Python: >=3.10
Requires-Dist: rich>=13.7.1
